testcase_automaker/__init__.py
testcase_automaker/Utils/__init__.py
testcase_automaker/Utils/httptools.py
testcase_automaker/Utils/amazingutils/__init__.py
testcase_automaker/Utils/amazingutils/randoms.py
testcase_automaker/interface/__init__.py
testcase_automaker/interface/http_params_generator.py
testcase_automaker/interface/http_tester.py
testcase_automaker-1.0.8.dist-info/LICENSE
testcase_automaker-1.0.8.dist-info/METADATA
testcase_automaker-1.0.8.dist-info/WHEEL
testcase_automaker-1.0.8.dist-info/top_level.txt
testcase_automaker-1.0.8.dist-info/RECORD
