Metadata-Version: 2.1
Name: testcase-automaker
Version: 1.0.8
Summary: testcase-automake base on pairwise
Home-page: https://github.com/amazingTest/testcase-automaker
Author: Yuyi Shao
Author-email: 523314409@qq.com
License: UNKNOWN
Platform: UNKNOWN
Classifier: Programming Language :: Python :: 3
Classifier: License :: OSI Approved :: GNU Affero General Public License v3 or later (AGPLv3+)
Classifier: Operating System :: OS Independent
